.DS_Store
rb_ipynb/__init__.py
rb_ipynb/extension.py
rb_ipynb/static/css/default.min.6926ad66fe81.css
rb_ipynb/static/css/default.min.css
rb_ipynb/static/css/vendor/notebook.6926ad66fe81.css
rb_ipynb/static/css/vendor/notebook.css
rb_ipynb/templates/rb_ipynb/ipynb.html
reviewboard_ipynb/__init__.py
reviewboard_ipynb/extension.py
reviewboard_ipynb/static/css/default.min.6926ad66fe81.css
reviewboard_ipynb/static/css/default.min.css
reviewboard_ipynb/static/css/default.min.d41d8cd98f00.css
reviewboard_ipynb/static/css/default.min.e1f8599dff94.css
reviewboard_ipynb/static/css/notebook.6926ad66fe81.css
reviewboard_ipynb/static/css/notebook.css
reviewboard_ipynb/static/css/notebook.e1f8599dff94.css
reviewboard_ipynb/templates/ipynb.html
reviewboard_ipynb-0.2.6.dist-info/LICENSE
reviewboard_ipynb-0.2.6.dist-info/METADATA
reviewboard_ipynb-0.2.6.dist-info/WHEEL
reviewboard_ipynb-0.2.6.dist-info/entry_points.txt
reviewboard_ipynb-0.2.6.dist-info/top_level.txt
reviewboard_ipynb-0.2.6.dist-info/RECORD
