Metadata-Version: 2.1
Name: reviewboard-ipynb
Version: 0.2.6
Summary: Display ipynb in a better format
Home-page: https://github.com/lydian/reviewboard-ipynb
Author: Lydian Lee
Author-email: lydianly@gmail.com
Maintainer: Lydian Lee
Maintainer-email: lydianly@gmail.com
License: UNKNOWN
Platform: UNKNOWN
Classifier: Development Status :: 4 - Beta
Classifier: Environment :: Web Environment
Classifier: Framework :: Review Board
Classifier: Intended Audience :: Developers
Classifier: License :: OSI Approved :: Apache Software License
Classifier: Natural Language :: English
Classifier: Operating System :: OS Independent
Classifier: Programming Language :: Python
Requires-Dist: beautifulsoup4
Requires-Dist: nbconvert
